shrm/__init__.py
shrm/data.py
shrm/test_data.py
shrm-0.1.1.dist-info/METADATA
shrm-0.1.1.dist-info/WHEEL
shrm-0.1.1.dist-info/top_level.txt
shrm-0.1.1.dist-info/RECORD
